image_manipulator/__init__.py
image_manipulator/processing/__init__.py
image_manipulator/processing/combination.py
image_manipulator/processing/transformation.py
image_manipulator/utils/__init__.py
image_manipulator/utils/io.py
image_manipulator/utils/plot.py
image_manipulator-0.0.1.dist-info/METADATA
image_manipulator-0.0.1.dist-info/WHEEL
image_manipulator-0.0.1.dist-info/top_level.txt
image_manipulator-0.0.1.dist-info/RECORD
