Metadata-Version: 2.1
Name: image-manipulator
Version: 0.0.1
Summary: pacote de manipulação de imagem
Home-page: https://github.com/aleeexp/Criando-um-pacote-no-PyPI
Author: Alex Pivato
Author-email: alexsnpivatoo@hotmail.com
Requires-Python: >=3.6
Requires-Dist: numpy
Requires-Dist: setuptools
Requires-Dist: matplotlib
Requires-Dist: scikit-image
